pyplutchik/__init__.py
pyplutchik/pyplutchik.py
pyplutchik-0.0.11.dist-info/METADATA
pyplutchik-0.0.11.dist-info/WHEEL
pyplutchik-0.0.11.dist-info/top_level.txt
pyplutchik-0.0.11.dist-info/RECORD
