Metadata-Version: 2.1
Name: pyplutchik
Version: 0.0.11
Summary: A library for visualizing emotions detected in corpora according to Plutchik's model.
Home-page: https://github.com/alfonsosemeraro/pyplutchik
Author: Alfonso Semeraro
Author-email: <alfonso.semeraro@gmail.com>
License: UNKNOWN
Keywords: python,dataviz,emotions,plutchik
Platform: UNKNOWN
Classifier: Development Status :: 3 - Alpha
Classifier: Intended Audience :: Science/Research
Classifier: License :: OSI Approved :: BSD License
Classifier: Programming Language :: Python :: 3
Requires-Dist: matplotlib
Requires-Dist: pandas
Requires-Dist: shapely
Requires-Dist: descartes
Requires-Dist: numpy
